MondayAPI/__init__.py
MondayAPI/__version__.py
MondayAPI/Exceptions/__init__.py
MondayAPI/Query/__init__.py
MondayAPI/Query/_datum.py
MondayAPI/Query/_node.py
MondayAPI/Query/boards.py
MondayAPI/Query/column_values.py
MondayAPI/Query/columns.py
MondayAPI/Query/items.py
MondayAPI/Query/items_page.py
MondayAPI/Query/next_items_page.py
MondayAPI/Query/query.py
MondayAPI/Query/subitems.py
MondayAPI/Query/users.py
mondayapi-0.1.1.dist-info/licenses/LICENSE
mondayapi-0.1.1.dist-info/METADATA
mondayapi-0.1.1.dist-info/WHEEL
mondayapi-0.1.1.dist-info/top_level.txt
mondayapi-0.1.1.dist-info/RECORD
