Metadata-Version: 2.4
Name: MondayAPI
Version: 0.1.1
Summary: Monday.com API Wrapper
Author-email: Carter Bodinger <carterallenbodinger@yahoo.com>
Project-URL: Homepage, https://github.com/cbodinge/MondayAPI
Project-URL: Issues, https://github.com/cbodinge/MondayAPI/issues
Keywords: api,monday
Classifier: Programming Language :: Python :: 3
Classifier: License :: OSI Approved :: MIT License
Classifier: Operating System :: OS Independent
Requires-Python: >=3.13
License-File: LICENSE
Dynamic: license-file
